seokxkyu_lotto/__init__.py
seokxkyu_lotto/draw.py
Seokxkyu_lotto-0.2.0.dist-info/METADATA
Seokxkyu_lotto-0.2.0.dist-info/WHEEL
Seokxkyu_lotto-0.2.0.dist-info/top_level.txt
Seokxkyu_lotto-0.2.0.dist-info/RECORD
